mlpet/__init__.py
mlpet/Datasets/__init__.py
mlpet/Datasets/feature_helpers.py
mlpet/Datasets/helpers.py
mlpet/Datasets/imputation_helpers.py
mlpet/Datasets/lithology.py
mlpet/Datasets/shear.py
MLPet-0.0.7.1.dist-info/LICENSE
MLPet-0.0.7.1.dist-info/METADATA
MLPet-0.0.7.1.dist-info/WHEEL
MLPet-0.0.7.1.dist-info/top_level.txt
MLPet-0.0.7.1.dist-info/RECORD
