Metadata-Version: 2.1
Name: MLPet
Version: 0.0.7.1
Summary: Package to prepare well log data for ML projects.
Home-page: https://bitbucket.org/akerbp/mlpet/
Author: Flavia Dias Casagrande
Author-email: flavia.dias.casagrande@akerbp.com
License: UNKNOWN
Platform: UNKNOWN
Classifier: Programming Language :: Python :: 3
Classifier: License :: OSI Approved :: MIT License
Classifier: Operating System :: OS Independent
Requires-Python: >=3.8
License-File: LICENSE
Requires-Dist: cognite-sdk (>=2.31.0)
Requires-Dist: imbalanced-learn (>=0.8.0)
Requires-Dist: joblib (==1.0.1)
Requires-Dist: numpy (>=1.19.5)
Requires-Dist: pandas (>=1.3.2)
Requires-Dist: scikit-learn (>=0.24.2)
Requires-Dist: scipy (>=1.7.1)
Requires-Dist: pyyaml
